Auraaisd/__init__.py
Auraaisd/aurai.py
Auraaisd-1.1.1.dist-info/METADATA
Auraaisd-1.1.1.dist-info/WHEEL
Auraaisd-1.1.1.dist-info/top_level.txt
Auraaisd-1.1.1.dist-info/RECORD
