Metadata-Version: 2.1
Name: Auraaisd
Version: 1.1.1
Summary: A ai packagage to make a wonderful ai enhancement
Author: Sandesh kumar
Author-email: ysd@gmail.com
License: mit liscence
Keywords: one,two
Classifier: Programming Language :: Python :: 3
Classifier: License :: OSI Approved :: MIT License
Classifier: Operating System :: OS Independent
Requires-Dist: requests
